pydustmasker/__init__.py
pydustmasker/_pydustmasker.cpython-313t-i386-linux-musl.so
pydustmasker/_pydustmasker.pyi
pydustmasker/py.typed
pydustmasker-2.0.0.dist-info/METADATA
pydustmasker-2.0.0.dist-info/WHEEL
pydustmasker-2.0.0.dist-info/licenses/LICENSE
pydustmasker.libs/libgcc_s-f5fcfe20.so.1
pydustmasker-2.0.0.dist-info/RECORD
