Metadata-Version: 2.4
Name: pydustmasker
Version: 2.0.0
License-File: LICENSE
Summary: Python bindings to DustMasker, a utility to identify and mask low-complexity regions in nucleotide sequences
Author-email: Antonio Camargo <antoniop.camargo@gmail.com>
License-Expression: MIT
Requires-Python: >=3.10
Project-URL: Home, https://github.com/apcamargo/pydustmasker
